binary_tree/BinaryTree.py
binary_tree/BinaryTreeNode.py
binary_tree/__init__.py
python_binary_tree-1.0.2.dist-info/licenses/LICENSE
python_binary_tree-1.0.2.dist-info/METADATA
python_binary_tree-1.0.2.dist-info/WHEEL
python_binary_tree-1.0.2.dist-info/top_level.txt
python_binary_tree-1.0.2.dist-info/RECORD
