Metadata-Version: 2.4
Name: python-binary-tree
Version: 1.0.2
Summary: Binary tree implementation for Python
Home-page: https://github.com/HangoverHGV/python-binary-tree
Author: HangoverHGV
License-File: LICENSE
Requires-Dist: networkx
Requires-Dist: matplotlib
Dynamic: author
Dynamic: description
Dynamic: description-content-type
Dynamic: home-page
Dynamic: license-file
Dynamic: requires-dist
Dynamic: summary
